smart_model_card/__init__.py
smart_model_card/athena_api.py
smart_model_card/cac.py
smart_model_card/cli.py
smart_model_card/data_sources.py
smart_model_card/exporters.py
smart_model_card/html_template.py
smart_model_card/integrations.py
smart_model_card/interactive.py
smart_model_card/model_card.py
smart_model_card/omop_reports.py
smart_model_card/provenance.py
smart_model_card/schema.py
smart_model_card/section_formatters.py
smart_model_card/sections.py
smart_model_card/visualizations.py
smart_model_card-2.0.0.dist-info/licenses/LICENSE
smart_model_card-2.0.0.dist-info/METADATA
smart_model_card-2.0.0.dist-info/WHEEL
smart_model_card-2.0.0.dist-info/entry_points.txt
smart_model_card-2.0.0.dist-info/top_level.txt
smart_model_card-2.0.0.dist-info/RECORD
