Metadata-Version: 2.4
Name: smart-model-card
Version: 2.0.0
Summary: A Python library for generating standardized AI/ML model cards with OMOP Common Data Model integration
Home-page: https://github.com/yourusername/smart-model-card
Author: Ankur Lohachab
Author-email: Ankur Lohachab <ankur.lohachab@maastrichtuniversity.nl>
License: MIT
Project-URL: Homepage, https://github.com/ankurlohachab/smart-model-card
Project-URL: Documentation, https://github.com/ankurlohachab/smart-model-card#readme
Project-URL: Repository, https://github.com/ankurlohachab/smart-model-card.git
Project-URL: Issues, https://github.com/ankurlohachab/smart-model-card/issues
Keywords: model card,OMOP,CDM,healthcare,machine learning,documentation
Classifier: Development Status :: 4 - Beta
Classifier: Intended Audience :: Science/Research
Classifier: Intended Audience :: Healthcare Industry
Classifier: License :: OSI Approved :: MIT License
Classifier: Programming Language :: Python :: 3
Classifier: Programming Language :: Python :: 3.8
Classifier: Programming Language :: Python :: 3.9
Classifier: Programming Language :: Python :: 3.10
Classifier: Programming Language :: Python :: 3.11
Classifier: Programming Language :: Python :: 3.12
Classifier: Topic :: Scientific/Engineering :: Medical Science Apps.
Classifier: Topic :: Software Development :: Documentation
Requires-Python: >=3.8
License-File: LICENSE
Requires-Dist: requests>=2.25.0
Provides-Extra: omop
Requires-Dist: smart-omop>=0.1.0; extra == "omop"
Requires-Dist: matplotlib>=3.3.0; extra == "omop"
Provides-Extra: viz
Requires-Dist: matplotlib>=3.3.0; extra == "viz"
Provides-Extra: dev
Requires-Dist: pytest>=6.0; extra == "dev"
Requires-Dist: pytest-cov; extra == "dev"
Requires-Dist: black; extra == "dev"
Requires-Dist: flake8; extra == "dev"
Provides-Extra: all
Requires-Dist: smart-model-card[dev,omop,viz]; extra == "all"
Dynamic: author
Dynamic: home-page
Dynamic: license-file
Dynamic: requires-python
